{"stat.useItem.minecraft.golden_apple":40,"stat.flyOneCm":50640,"stat.deaths":60,"stat.walkOneCm":59255,"stat.jump":4080,"stat.playerKills":40,"stat.playOneMinute":130220,"stat.fallOneCm":4971,"stat.useItem.minecraft.iron_sword":120,"stat.leaveGame":20,"stat.damageTaken":10594,"stat.damageDealt":525,"stat.useItem.minecraft.wool":1260,"stat.crouchOneCm":295,"stat.mineBlock.minecraft.wool":20,"stat.timeSinceDeath":16620,"stat.sprintOneCm":47249,"achievement.exploreAllBiomes":{"value":0,"progress":["Plains"]}}